{
  "name": {
    "de": "AV gem. Art. 30 II DS-GVO"
  },
  "description": {
    "de": "Dokumentation 체ber die Auftraggeber und f체r sie durchgef체hrte Verarbeitungst채tigkeiten (Auftragsverarbeitung)"
  },
  "templateFile": "av.md",
  "templateType": "text/markdown",
  "outputTypes": [
    "application/pdf"
  ],
  "targetTypes": [
    {
      "modelType": "scope",
      "subTypes": [
        "SCP_ResponsibleBody"
      ]
    }
  ],
  "data": {
    "scope": "/scopes/${targetId}",
    "scopes": "/scopes?size=2147483647",
    "processes": "/processes?size=2147483647",
    "persons": "/persons?size=2147483647"
  }
}